{
    "movies": [
        {
            "id": "1",
            "title": "Wrong Side Raju (2016) DvDRip x264 ESubs 400MB",
            "img": "https://2.bp.blogspot.com/-TSm7QZAktIw/Wx1JWfJgRDI/AAAAAAAAFgo/h-O-XWG2kBMxZYV3nsJeFaZyl1qc78DegCLcBGAs/s1600/2017.jpg",
            "type": "gj",
            "ss": [
                "https://4.bp.blogspot.com/-c182QwEx52g/Wx1KGJnOKsI/AAAAAAAAFg4/YxRqLuhreBoK7PLrVVuIOfVsPwy5FU0VwCLcBGAs/s1600/image-2.png"
            ],
            "download": {
                "name": "openload",
                "link": "sss"
            }
        },
        {
            "id": "2",
            "title": "love ni bhavai",
            "img": "https://1.bp.blogspot.com/-qjhFBbHq_5Y/Wx2N45JP9YI/AAAAAAAAFhw/AHMYhZfCZUMpPrbSTJ9dzb5VdcMu83HnACLcBGAs/s400/2017.jpg",
            "type": "gj",
            "ss": [
                "https://4.bp.blogspot.com/-lit6FzZCyY4/Wx2Xu018rGI/AAAAAAAAFiE/ma_5wMlwx4gdoeRJtXOMme75FUrY9e93QCLcBGAs/s1600/image-2.png"
            ],
            "download": {
                "name": "https://openload.co/f/_oDzo2rkaOM",
                "deciUploade": "https://desiupload.me/ey0zfs199ud8"
            }
        },
        {
            "id": "3",
            "title": "xyz",
            "img": "https://shivampatel.ml/img/prakarsh2-min.JPG",
            "type": "bw",
            "ss": [
                "https://shivampatel.ml/img/prakarsh2-min.JPG",
                "https://shivampatel.ml/img/prakarsh2-min.JPG"
            ],
            "download": {
                "name": "openload",
                "link": "sss"
            }
        },
        {
            "id": "4",
            "title": "xyz",
            "img": "https://shivampatel.ml/img/prakarsh2-min.JPG",
            "type": "hw",
            "ss": [
                "https://shivampatel.ml/img/prakarsh2-min.JPG",
                "https://shivampatel.ml/img/prakarsh2-min.JPG",
                "https://shivampatel.ml/img/prakarsh2-min.JPG",
                "https://shivampatel.ml/img/prakarsh2-min.JPG"
            ],
            "download": {
                "name": "openload",
                "link": "sss"
            }
        }
    ]
}
